fastscore/R.py
fastscore/__init__.py
fastscore/_schemer.py
fastscore/_version.py
fastscore/attachment.py
fastscore/constants.py
fastscore/errors.py
fastscore/model.py
fastscore/pneumo.py
fastscore/schema.py
fastscore/sensor.py
fastscore/snapshot.py
fastscore/stream.py
fastscore/version.py
fastscore/io/Slot.py
fastscore/io/__init__.py
fastscore/suite/__init__.py
fastscore/suite/connect.py
fastscore/suite/engine.py
fastscore/suite/instance.py
fastscore/suite/model_manage.py
fastscore/utils/__init__.py
fastscore/utils/secrets.py
fastscore/utils/utils.py
fastscore/v1/__init__.py
fastscore/v1/api_client.py
fastscore/v1/configuration.py
fastscore/v1/rest.py
fastscore/v1/apis/__init__.py
fastscore/v1/apis/connect_api.py
fastscore/v1/apis/engine_api.py
fastscore/v1/apis/login_api.py
fastscore/v1/apis/model_manage_api.py
fastscore/v1/models/__init__.py
fastscore/v1/models/cpu_usage_info.py
fastscore/v1/models/cpu_usage_info_jets.py
fastscore/v1/models/cpu_usage_info_op_times.py
fastscore/v1/models/health_info.py
fastscore/v1/models/inline_response_200.py
fastscore/v1/models/inline_response_200_1.py
fastscore/v1/models/inline_response_200_2.py
fastscore/v1/models/inline_response_200_3.py
fastscore/v1/models/instance_info.py
fastscore/v1/models/manifold_info.py
fastscore/v1/models/manifold_info_jets.py
fastscore/v1/models/manifold_info_model.py
fastscore/v1/models/manifold_info_slots.py
fastscore/v1/models/manifold_info_stream.py
fastscore/v1/models/verify_info.py
fastscore/v1/models/verify_info_slots.py
fastscore/v2/__init__.py
fastscore/v2/api_client.py
fastscore/v2/configuration.py
fastscore/v2/rest.py
fastscore/v2/apis/__init__.py
fastscore/v2/apis/connect_api.py
fastscore/v2/apis/engine_api.py
fastscore/v2/apis/model_manage_api.py
fastscore/v2/models/__init__.py
fastscore/v2/models/active_model_info.py
fastscore/v2/models/active_sensor_info.py
fastscore/v2/models/active_stream_info.py
fastscore/v2/models/inline_response_200.py
fastscore/v2/models/inline_response_200_1.py
fastscore-1.10.3.dist-info/METADATA
fastscore-1.10.3.dist-info/WHEEL
fastscore-1.10.3.dist-info/top_level.txt
fastscore-1.10.3.dist-info/RECORD
